fftrack/__init__.py
fftrack/__main__.py
fftrack/config.json
fftrack/config.py
fftrack/main.py
fftrack/audio/__init__.py
fftrack/audio/audio_compare.py
fftrack/audio/audio_processing.py
fftrack/audio/audio_reader.py
fftrack/audio/main_audio.py
fftrack/database/__init__.py
fftrack/database/db_manager.py
fftrack/database/main_db.py
fftrack/database/models.py
fftrack/matching/__init__.py
fftrack/matching/main_matching.py
fftrack/matching/matcher.py
fftrack/scripts/__init__.py
fftrack/scripts/populate_database.py
fftrack/scripts/songs_to_download.csv
fftrack/ui/__init__.py
fftrack/ui/cli.py
fftrack/ui/main_cli.py
fftrack-0.2.0.dist-info/METADATA
fftrack-0.2.0.dist-info/WHEEL
fftrack-0.2.0.dist-info/entry_points.txt
fftrack-0.2.0.dist-info/top_level.txt
fftrack-0.2.0.dist-info/RECORD
